AUTHORS
ChangeLog
LICENSE
MANIFEST.in
README.md
setup.py
papa/__init__.py
papa/utils.py
papa.egg-info/PKG-INFO
papa.egg-info/SOURCES.txt
papa.egg-info/dependency_links.txt
papa.egg-info/entry_points.txt
papa.egg-info/top_level.txt
papa.egg-info/zip-safe
papa/server/__init__.py
papa/server/papa_socket.py
papa/server/proc.py
papa/server/values.py
tests/__init__.py